{
  "name": "Buttered Muffins",
  "season_completed": false,
  "season_name": "",
  "team_number": 2044,
  "season_number": 32,
  "league_number": 1,
  "league": "SIAHL@SJ Senior C",
  "siahl_sj_league": "C",
  "start_date": "2015-04-16",
  "end_date": "2015-07-30",
  "games": [
    {
      "game_id": 132751,
      "date": "2015-04-16",
      "datetime": "2015-04-16T22:30:00-08:00",
      "date_string": "Thu Apr 16",
      "time_string": "10:30 PM",
      "rink": "San Jose East",
      "hockey_league_name": "SIAHL@SJ",
      "division_name": "Senior C",
      "league": "SIAHL@SJ Senior C",
      "siahl_sj_league": "C",
      "visitor_team_name": "Buttered Muffins",
      "visitor_goals": 9,
      "visitor_goals_string": "9",
      "home_team_name": "Sasquatch",
      "home_goals": 5,
      "home_goals_string": "5",
      "game_won_in_shootout": false,
      "game_won_in_overtime": false,
      "type": "Preseason"
    },
    {
      "game_id": 132969,
      "date": "2015-05-01",
      "datetime": "2015-05-01T23:00:00-08:00",
      "date_string": "Fri May 1",
      "time_string": "11:00 PM",
      "rink": "San Jose North",
      "hockey_league_name": "SIAHL@SJ",
      "division_name": "Senior C",
      "league": "SIAHL@SJ Senior C",
      "siahl_sj_league": "C",
      "visitor_team_name": "Buttered Muffins",
      "visitor_goals": 0,
      "visitor_goals_string": "0",
      "home_team_name": "OHC",
      "home_goals": 6,
      "home_goals_string": "6",
      "game_won_in_shootout": false,
      "game_won_in_overtime": false,
      "type": "Preseason"
    },
    {
      "game_id": 133184,
      "date": "2015-05-07",
      "datetime": "2015-05-07T21:45:00-08:00",
      "date_string": "Thu May 7",
      "time_string": "9:45 PM",
      "rink": "San Jose South",
      "hockey_league_name": "SIAHL@SJ",
      "division_name": "Senior C",
      "league": "SIAHL@SJ Senior C",
      "siahl_sj_league": "C",
      "visitor_team_name": "Roughriders",
      "visitor_goals": 9,
      "visitor_goals_string": "9",
      "home_team_name": "Buttered Muffins",
      "home_goals": 5,
      "home_goals_string": "5",
      "game_won_in_shootout": false,
      "game_won_in_overtime": false,
      "type": "Regular"
    },
    {
      "game_id": 133267,
      "date": "2015-05-14",
      "datetime": "2015-05-14T18:30:00-08:00",
      "date_string": "Thu May 14",
      "time_string": "6:30 PM",
      "rink": "San Jose East",
      "hockey_league_name": "SIAHL@SJ",
      "division_name": "Senior C",
      "league": "SIAHL@SJ Senior C",
      "siahl_sj_league": "C",
      "visitor_team_name": "Norcal Leafs",
      "visitor_goals": 4,
      "visitor_goals_string": "4 S",
      "home_team_name": "Buttered Muffins",
      "home_goals": 5,
      "home_goals_string": "5",
      "game_won_in_shootout": true,
      "game_won_in_overtime": false,
      "type": "Regular"
    },
    {
      "game_id": 133850,
      "date": "2015-05-21",
      "datetime": "2015-05-21T23:15:00-08:00",
      "date_string": "Thu May 21",
      "time_string": "11:15 PM",
      "rink": "San Jose North",
      "hockey_league_name": "SIAHL@SJ",
      "division_name": "Senior C",
      "league": "SIAHL@SJ Senior C",
      "siahl_sj_league": "C",
      "visitor_team_name": "Reapers",
      "visitor_goals": 5,
      "visitor_goals_string": "5",
      "home_team_name": "Buttered Muffins",
      "home_goals": 7,
      "home_goals_string": "7",
      "game_won_in_shootout": false,
      "game_won_in_overtime": false,
      "type": "Regular"
    },
    {
      "game_id": 133962,
      "date": "2015-05-28",
      "datetime": "2015-05-28T20:15:00-08:00",
      "date_string": "Thu May 28",
      "time_string": "8:15 PM",
      "rink": "San Jose North",
      "hockey_league_name": "SIAHL@SJ",
      "division_name": "Senior C",
      "league": "SIAHL@SJ Senior C",
      "siahl_sj_league": "C",
      "visitor_team_name": "Buttered Muffins",
      "visitor_goals": 4,
      "visitor_goals_string": "4",
      "home_team_name": "Lost Eskimos",
      "home_goals": 6,
      "home_goals_string": "6",
      "game_won_in_shootout": false,
      "game_won_in_overtime": false,
      "type": "Regular"
    },
    {
      "game_id": 134230,
      "date": "2015-06-05",
      "datetime": "2015-06-05T22:00:00-08:00",
      "date_string": "Fri Jun 5",
      "time_string": "10:00 PM",
      "rink": "San Jose East",
      "hockey_league_name": "SIAHL@SJ",
      "division_name": "Senior C",
      "league": "SIAHL@SJ Senior C",
      "siahl_sj_league": "C",
      "visitor_team_name": "Isotopes",
      "visitor_goals": 3,
      "visitor_goals_string": "3 S",
      "home_team_name": "Buttered Muffins",
      "home_goals": 4,
      "home_goals_string": "4",
      "game_won_in_shootout": true,
      "game_won_in_overtime": false,
      "type": "Regular"
    },
    {
      "game_id": 134312,
      "date": "2015-06-12",
      "datetime": "2015-06-12T21:45:00-08:00",
      "date_string": "Fri Jun 12",
      "time_string": "9:45 PM",
      "rink": "San Jose South",
      "hockey_league_name": "SIAHL@SJ",
      "division_name": "Senior C",
      "league": "SIAHL@SJ Senior C",
      "siahl_sj_league": "C",
      "visitor_team_name": "Buttered Muffins",
      "visitor_goals": 4,
      "visitor_goals_string": "4",
      "home_team_name": "Roughriders",
      "home_goals": 6,
      "home_goals_string": "6",
      "game_won_in_shootout": false,
      "game_won_in_overtime": false,
      "type": "Regular"
    },
    {
      "game_id": 134401,
      "date": "2015-06-17",
      "datetime": "2015-06-17T23:15:00-08:00",
      "date_string": "Wed Jun 17",
      "time_string": "11:15 PM",
      "rink": "San Jose East",
      "hockey_league_name": "SIAHL@SJ",
      "division_name": "Senior C",
      "league": "SIAHL@SJ Senior C",
      "siahl_sj_league": "C",
      "visitor_team_name": "Buttered Muffins",
      "visitor_goals": 5,
      "visitor_goals_string": "5",
      "home_team_name": "OHC",
      "home_goals": 4,
      "home_goals_string": "4",
      "game_won_in_shootout": false,
      "game_won_in_overtime": false,
      "type": "Regular"
    },
    {
      "game_id": 134444,
      "date": "2015-06-20",
      "datetime": "2015-06-20T14:30:00-08:00",
      "date_string": "Sat Jun 20",
      "time_string": "2:30 PM",
      "rink": "San Jose East",
      "hockey_league_name": "SIAHL@SJ",
      "division_name": "Senior C",
      "league": "SIAHL@SJ Senior C",
      "siahl_sj_league": "C",
      "visitor_team_name": "Buttered Muffins",
      "visitor_goals": 6,
      "visitor_goals_string": "6",
      "home_team_name": "Lost Eskimos",
      "home_goals": 7,
      "home_goals_string": "7",
      "game_won_in_shootout": false,
      "game_won_in_overtime": false,
      "type": "Regular"
    },
    {
      "game_id": 134532,
      "date": "2015-06-26",
      "datetime": "2015-06-26T20:15:00-08:00",
      "date_string": "Fri Jun 26",
      "time_string": "8:15 PM",
      "rink": "San Jose East",
      "hockey_league_name": "SIAHL@SJ",
      "division_name": "Senior C",
      "league": "SIAHL@SJ Senior C",
      "siahl_sj_league": "C",
      "visitor_team_name": "Norcal Leafs",
      "visitor_goals": 4,
      "visitor_goals_string": "4",
      "home_team_name": "Buttered Muffins",
      "home_goals": 2,
      "home_goals_string": "2",
      "game_won_in_shootout": false,
      "game_won_in_overtime": false,
      "type": "Regular"
    },
    {
      "game_id": 134701,
      "date": "2015-07-03",
      "datetime": "2015-07-03T20:15:00-08:00",
      "date_string": "Fri Jul 3",
      "time_string": "8:15 PM",
      "rink": "San Jose South",
      "hockey_league_name": "SIAHL@SJ",
      "division_name": "Senior C",
      "league": "SIAHL@SJ Senior C",
      "siahl_sj_league": "C",
      "visitor_team_name": "Buttered Muffins",
      "visitor_goals": 10,
      "visitor_goals_string": "10",
      "home_team_name": "Roughriders",
      "home_goals": 6,
      "home_goals_string": "6",
      "game_won_in_shootout": false,
      "game_won_in_overtime": false,
      "type": "Regular"
    },
    {
      "game_id": 134840,
      "date": "2015-07-10",
      "datetime": "2015-07-10T21:45:00-08:00",
      "date_string": "Fri Jul 10",
      "time_string": "9:45 PM",
      "rink": "San Jose Center",
      "hockey_league_name": "SIAHL@SJ",
      "division_name": "Senior C",
      "league": "SIAHL@SJ Senior C",
      "siahl_sj_league": "C",
      "visitor_team_name": "Buttered Muffins",
      "visitor_goals": 4,
      "visitor_goals_string": "4",
      "home_team_name": "Isotopes",
      "home_goals": 2,
      "home_goals_string": "2",
      "game_won_in_shootout": false,
      "game_won_in_overtime": false,
      "type": "Regular"
    },
    {
      "game_id": 135037,
      "date": "2015-07-18",
      "datetime": "2015-07-18T11:30:00-08:00",
      "date_string": "Sat Jul 18",
      "time_string": "11:30 AM",
      "rink": "San Jose South",
      "hockey_league_name": "SIAHL@SJ",
      "division_name": "Senior C",
      "league": "SIAHL@SJ Senior C",
      "siahl_sj_league": "C",
      "visitor_team_name": "Reapers",
      "visitor_goals": 0,
      "visitor_goals_string": "0",
      "home_team_name": "Buttered Muffins",
      "home_goals": 3,
      "home_goals_string": "3",
      "game_won_in_shootout": false,
      "game_won_in_overtime": false,
      "type": "Regular"
    },
    {
      "game_id": 135715,
      "date": "2015-07-24",
      "datetime": "2015-07-24T21:45:00-08:00",
      "date_string": "Fri Jul 24",
      "time_string": "9:45 PM",
      "rink": "San Jose South",
      "hockey_league_name": "SIAHL@SJ",
      "division_name": "Senior C",
      "league": "SIAHL@SJ Senior C",
      "siahl_sj_league": "C",
      "visitor_team_name": "Reapers",
      "visitor_goals": 3,
      "visitor_goals_string": "3",
      "home_team_name": "Buttered Muffins",
      "home_goals": 9,
      "home_goals_string": "9",
      "game_won_in_shootout": false,
      "game_won_in_overtime": false,
      "type": "Regular"
    },
    {
      "game_id": 135993,
      "date": "2015-07-30",
      "datetime": "2015-07-30T21:00:00-08:00",
      "date_string": "Thu Jul 30",
      "time_string": "9:00 PM",
      "rink": "San Jose East",
      "hockey_league_name": "SIAHL@SJ",
      "division_name": "Senior C",
      "league": "SIAHL@SJ Senior C",
      "siahl_sj_league": "C",
      "visitor_team_name": "Buttered Muffins",
      "visitor_goals": 6,
      "visitor_goals_string": "6",
      "home_team_name": "OHC",
      "home_goals": 4,
      "home_goals_string": "4",
      "game_won_in_shootout": false,
      "game_won_in_overtime": false,
      "type": "Regular"
    },
    {
      "game_id": "136025",
      "date": "2015-08-07",
      "datetime": "2015-08-07T20:30:00-08:00",
      "date_string": "Fri Aug 7",
      "time_string": "8:30 PM",
      "rink": "San Jose South",
      "hockey_league_name": "SIAHL@SJ",
      "division_name": "Senior C",
      "league": "SIAHL@SJ Senior C",
      "siahl_sj_league": "C",
      "visitor_team_name": "Buttered Muffins",
      "visitor_goals": 1,
      "visitor_goals_string": 1,
      "home_team_name": "OHC",
      "home_goals": 9,
      "home_goals_string": 9,
      "game_won_in_shootout": false,
      "game_won_in_overtime": false,
      "type": "Regular"
    },
    {
      "game_id": "136180",
      "date": "",
      "datetime": "",
      "date_string": "Sat Aug 15",
      "time_string": "9:15 PM",
      "rink": "San Jose North",
      "hockey_league_name": "SIAHL@SJ",
      "division_name": "Senior C",
      "league": "SIAHL@SJ Senior C",
      "siahl_sj_league": "C",
      "visitor_team_name": "Norcal Leafs",
      "visitor_goals": 0,
      "visitor_goals_string": "",
      "home_team_name": "Buttered Muffins",
      "home_goals": 0,
      "home_goals_string": "",
      "game_won_in_shootout": false,
      "game_won_in_overtime": false,
      "type": "Regular"
    }
  ],
  "skaters": [
    {
      "name": "Gage Emerson",
      "number": "8",
      "rostered_player": true,
      "games_played": 11,
      "goals": 18,
      "assists": 13,
      "power_play_goals": 1,
      "power_play_assists": 1,
      "short_handed_goals": 1,
      "short_handed_assists": 1,
      "game_winning_goal": 2,
      "game_winning_assists": 1,
      "penalty_shot_goals": 0,
      "empty_net_goals": 0,
      "shots_on_goal": 0,
      "is_goalie": false
    },
    {
      "name": "Kirby Haraguchi",
      "number": "16",
      "rostered_player": true,
      "games_played": 7,
      "goals": 12,
      "assists": 10,
      "power_play_goals": 1,
      "power_play_assists": 0,
      "short_handed_goals": 0,
      "short_handed_assists": 0,
      "game_winning_goal": 1,
      "game_winning_assists": 1,
      "penalty_shot_goals": 0,
      "empty_net_goals": 1,
      "shots_on_goal": 0,
      "is_goalie": false
    },
    {
      "name": "Michael LaGrange",
      "number": "44",
      "rostered_player": true,
      "games_played": 9,
      "goals": 8,
      "assists": 6,
      "power_play_goals": 0,
      "power_play_assists": 0,
      "short_handed_goals": 0,
      "short_handed_assists": 0,
      "game_winning_goal": 0,
      "game_winning_assists": 1,
      "penalty_shot_goals": 0,
      "empty_net_goals": 1,
      "shots_on_goal": 0,
      "is_goalie": false
    },
    {
      "name": "Michael Hughes",
      "number": "68",
      "rostered_player": true,
      "games_played": 10,
      "goals": 3,
      "assists": 7,
      "power_play_goals": 1,
      "power_play_assists": 0,
      "short_handed_goals": 1,
      "short_handed_assists": 0,
      "game_winning_goal": 0,
      "game_winning_assists": 1,
      "penalty_shot_goals": 0,
      "empty_net_goals": 0,
      "shots_on_goal": 0,
      "is_goalie": false
    },
    {
      "name": "Stephen Howe",
      "number": "88",
      "rostered_player": true,
      "games_played": 6,
      "goals": 2,
      "assists": 4,
      "power_play_goals": 1,
      "power_play_assists": 1,
      "short_handed_goals": 0,
      "short_handed_assists": 0,
      "game_winning_goal": 0,
      "game_winning_assists": 0,
      "penalty_shot_goals": 0,
      "empty_net_goals": 0,
      "shots_on_goal": 0,
      "is_goalie": false
    },
    {
      "name": "Paul Mulholland",
      "number": "96",
      "rostered_player": true,
      "games_played": 4,
      "goals": 2,
      "assists": 4,
      "power_play_goals": 0,
      "power_play_assists": 0,
      "short_handed_goals": 0,
      "short_handed_assists": 1,
      "game_winning_goal": 0,
      "game_winning_assists": 1,
      "penalty_shot_goals": 0,
      "empty_net_goals": 0,
      "shots_on_goal": 0,
      "is_goalie": false
    },
    {
      "name": "Chris Rathjen",
      "number": "39",
      "rostered_player": true,
      "games_played": 8,
      "goals": 1,
      "assists": 4,
      "power_play_goals": 0,
      "power_play_assists": 0,
      "short_handed_goals": 0,
      "short_handed_assists": 0,
      "game_winning_goal": 1,
      "game_winning_assists": 0,
      "penalty_shot_goals": 0,
      "empty_net_goals": 0,
      "shots_on_goal": 0,
      "is_goalie": false
    },
    {
      "name": "Mark Yost",
      "number": "13",
      "rostered_player": true,
      "games_played": 4,
      "goals": 2,
      "assists": 3,
      "power_play_goals": 0,
      "power_play_assists": 1,
      "short_handed_goals": 0,
      "short_handed_assists": 0,
      "game_winning_goal": 0,
      "game_winning_assists": 0,
      "penalty_shot_goals": 0,
      "empty_net_goals": 0,
      "shots_on_goal": 0,
      "is_goalie": false
    },
    {
      "name": "Johnny Brafford",
      "number": "5",
      "rostered_player": true,
      "games_played": 8,
      "goals": 4,
      "assists": 0,
      "power_play_goals": 0,
      "power_play_assists": 0,
      "short_handed_goals": 0,
      "short_handed_assists": 0,
      "game_winning_goal": 1,
      "game_winning_assists": 0,
      "penalty_shot_goals": 0,
      "empty_net_goals": 0,
      "shots_on_goal": 0,
      "is_goalie": false
    },
    {
      "name": "Marcus Delong",
      "number": "10",
      "rostered_player": true,
      "games_played": 7,
      "goals": 0,
      "assists": 4,
      "power_play_goals": 0,
      "power_play_assists": 0,
      "short_handed_goals": 0,
      "short_handed_assists": 0,
      "game_winning_goal": 0,
      "game_winning_assists": 0,
      "penalty_shot_goals": 0,
      "empty_net_goals": 0,
      "shots_on_goal": 0,
      "is_goalie": false
    },
    {
      "name": "Andrew Morton",
      "number": "28",
      "rostered_player": true,
      "games_played": 6,
      "goals": 1,
      "assists": 3,
      "power_play_goals": 0,
      "power_play_assists": 0,
      "short_handed_goals": 0,
      "short_handed_assists": 0,
      "game_winning_goal": 0,
      "game_winning_assists": 0,
      "penalty_shot_goals": 0,
      "empty_net_goals": 0,
      "shots_on_goal": 0,
      "is_goalie": false
    },
    {
      "name": "Martin Boyd",
      "number": "17",
      "rostered_player": true,
      "games_played": 4,
      "goals": 2,
      "assists": 1,
      "power_play_goals": 0,
      "power_play_assists": 0,
      "short_handed_goals": 0,
      "short_handed_assists": 0,
      "game_winning_goal": 1,
      "game_winning_assists": 0,
      "penalty_shot_goals": 0,
      "empty_net_goals": 0,
      "shots_on_goal": 0,
      "is_goalie": false
    },
    {
      "name": "Bret Erwin",
      "number": "52",
      "rostered_player": true,
      "games_played": 6,
      "goals": 1,
      "assists": 2,
      "power_play_goals": 0,
      "power_play_assists": 0,
      "short_handed_goals": 0,
      "short_handed_assists": 1,
      "game_winning_goal": 0,
      "game_winning_assists": 0,
      "penalty_shot_goals": 0,
      "empty_net_goals": 0,
      "shots_on_goal": 0,
      "is_goalie": false
    },
    {
      "name": "omar sandhu",
      "number": "19",
      "rostered_player": true,
      "games_played": 3,
      "goals": 2,
      "assists": 1,
      "power_play_goals": 0,
      "power_play_assists": 0,
      "short_handed_goals": 0,
      "short_handed_assists": 0,
      "game_winning_goal": 0,
      "game_winning_assists": 1,
      "penalty_shot_goals": 0,
      "empty_net_goals": 0,
      "shots_on_goal": 0,
      "is_goalie": false
    },
    {
      "name": "Robert Anderson",
      "number": "",
      "rostered_player": false,
      "games_played": 2,
      "goals": 1,
      "assists": 1,
      "power_play_goals": 0,
      "power_play_assists": 0,
      "short_handed_goals": 0,
      "short_handed_assists": 0,
      "game_winning_goal": 0,
      "game_winning_assists": 0,
      "penalty_shot_goals": 0,
      "empty_net_goals": 0,
      "shots_on_goal": 0,
      "is_goalie": false
    },
    {
      "name": "Kevin Jiang",
      "number": "24",
      "rostered_player": true,
      "games_played": 8,
      "goals": 0,
      "assists": 2,
      "power_play_goals": 0,
      "power_play_assists": 2,
      "short_handed_goals": 0,
      "short_handed_assists": 0,
      "game_winning_goal": 0,
      "game_winning_assists": 0,
      "penalty_shot_goals": 0,
      "empty_net_goals": 0,
      "shots_on_goal": 0,
      "is_goalie": false
    },
    {
      "name": "Kenneth Nishikawa",
      "number": "14",
      "rostered_player": true,
      "games_played": 7,
      "goals": 0,
      "assists": 2,
      "power_play_goals": 0,
      "power_play_assists": 0,
      "short_handed_goals": 0,
      "short_handed_assists": 0,
      "game_winning_goal": 0,
      "game_winning_assists": 1,
      "penalty_shot_goals": 0,
      "empty_net_goals": 0,
      "shots_on_goal": 0,
      "is_goalie": false
    },
    {
      "name": "Doug Harvey",
      "number": "2",
      "rostered_player": true,
      "games_played": 3,
      "goals": 0,
      "assists": 1,
      "power_play_goals": 0,
      "power_play_assists": 0,
      "short_handed_goals": 0,
      "short_handed_assists": 0,
      "game_winning_goal": 0,
      "game_winning_assists": 0,
      "penalty_shot_goals": 0,
      "empty_net_goals": 0,
      "shots_on_goal": 0,
      "is_goalie": false
    },
    {
      "name": "Chad Hyatt",
      "number": "97",
      "rostered_player": true,
      "games_played": 3,
      "goals": 1,
      "assists": 0,
      "power_play_goals": 0,
      "power_play_assists": 0,
      "short_handed_goals": 0,
      "short_handed_assists": 0,
      "game_winning_goal": 0,
      "game_winning_assists": 0,
      "penalty_shot_goals": 0,
      "empty_net_goals": 0,
      "shots_on_goal": 0,
      "is_goalie": false
    },
    {
      "name": "Jason Webster",
      "number": "55",
      "rostered_player": true,
      "games_played": 3,
      "goals": 1,
      "assists": 0,
      "power_play_goals": 0,
      "power_play_assists": 0,
      "short_handed_goals": 0,
      "short_handed_assists": 0,
      "game_winning_goal": 0,
      "game_winning_assists": 0,
      "penalty_shot_goals": 0,
      "empty_net_goals": 0,
      "shots_on_goal": 0,
      "is_goalie": false
    },
    {
      "name": "Garrett Zumbrunnen",
      "number": "88",
      "rostered_player": true,
      "games_played": 2,
      "goals": 1,
      "assists": 0,
      "power_play_goals": 0,
      "power_play_assists": 0,
      "short_handed_goals": 0,
      "short_handed_assists": 0,
      "game_winning_goal": 0,
      "game_winning_assists": 0,
      "penalty_shot_goals": 0,
      "empty_net_goals": 0,
      "shots_on_goal": 0,
      "is_goalie": false
    },
    {
      "name": "Justin Anonas",
      "number": "",
      "rostered_player": false,
      "games_played": 1,
      "goals": 0,
      "assists": 0,
      "power_play_goals": 0,
      "power_play_assists": 0,
      "short_handed_goals": 0,
      "short_handed_assists": 0,
      "game_winning_goal": 0,
      "game_winning_assists": 0,
      "penalty_shot_goals": 0,
      "empty_net_goals": 0,
      "shots_on_goal": 0,
      "is_goalie": false
    },
    {
      "name": "Linda Anonas",
      "number": "",
      "rostered_player": false,
      "games_played": 1,
      "goals": 0,
      "assists": 0,
      "power_play_goals": 0,
      "power_play_assists": 0,
      "short_handed_goals": 0,
      "short_handed_assists": 0,
      "game_winning_goal": 0,
      "game_winning_assists": 0,
      "penalty_shot_goals": 0,
      "empty_net_goals": 0,
      "shots_on_goal": 0,
      "is_goalie": false
    }
  ],
  "goalies": [
    {
      "name": "Devin R Dinardo",
      "number": "38",
      "rostered_player": true,
      "games_played": 2,
      "shots_against": 68,
      "goals_against": 15,
      "goals_against_average": 7.5,
      "save_percentage": 0.779,
      "goals": 0,
      "assists": 0,
      "points": 0,
      "is_goalie": true
    },
    {
      "name": "",
      "number": "",
      "rostered_player": false,
      "games_played": 2,
      "shots_against": 56,
      "goals_against": 11,
      "goals_against_average": 5.5,
      "save_percentage": 0.804,
      "goals": 0,
      "assists": 0,
      "points": 0,
      "is_goalie": true
    },
    {
      "name": "Justin A Tarabanovic",
      "number": "45",
      "rostered_player": true,
      "games_played": 10,
      "shots_against": 303,
      "goals_against": 37,
      "goals_against_average": 3.7,
      "save_percentage": 0.878,
      "goals": 0,
      "assists": 0,
      "points": 0,
      "is_goalie": true
    }
  ]
}
