{
  "name": "Raccoons 2",
  "season_completed": false,
  "season_name": "",
  "team_number": 2267,
  "season_number": 32,
  "league_number": 1,
  "league": "SIAHL@SJ Senior DDDDD West",
  "siahl_sj_league": "DDDDD",
  "start_date": "2015-04-18",
  "end_date": "2015-08-02",
  "games": [
    {
      "game_id": 133044,
      "date": "2015-04-18",
      "datetime": "2015-04-18T17:30:00-08:00",
      "date_string": "Sat Apr 18",
      "time_string": "5:30 PM",
      "rink": "San Jose South",
      "hockey_league_name": "SIAHL@SJ",
      "division_name": "Senior DDDDD",
      "league": "SIAHL@SJ Senior DDDDD",
      "siahl_sj_league": "DDDDD",
      "visitor_team_name": "Raccoons 2",
      "visitor_goals": 0,
      "visitor_goals_string": "0",
      "home_team_name": "Tyrannosaurs",
      "home_goals": 4,
      "home_goals_string": "4",
      "game_won_in_shootout": false,
      "game_won_in_overtime": false,
      "type": "Preseason"
    },
    {
      "game_id": 132885,
      "date": "2015-04-21",
      "datetime": "2015-04-21T21:45:00-08:00",
      "date_string": "Tue Apr 21",
      "time_string": "9:45 PM",
      "rink": "San Jose South",
      "hockey_league_name": "SIAHL@SJ",
      "division_name": "Senior DDDDD",
      "league": "SIAHL@SJ Senior DDDDD",
      "siahl_sj_league": "DDDDD",
      "visitor_team_name": "Dunder Mifflin",
      "visitor_goals": 5,
      "visitor_goals_string": "5",
      "home_team_name": "Raccoons 2",
      "home_goals": 3,
      "home_goals_string": "3",
      "game_won_in_shootout": false,
      "game_won_in_overtime": false,
      "type": "Preseason"
    },
    {
      "game_id": 133148,
      "date": "2015-05-03",
      "datetime": "2015-05-03T18:45:00-08:00",
      "date_string": "Sun May 3",
      "time_string": "6:45 PM",
      "rink": "San Jose Center",
      "hockey_league_name": "SIAHL@SJ",
      "division_name": "Senior DDDDD",
      "league": "SIAHL@SJ Senior DDDDD",
      "siahl_sj_league": "DDDDD",
      "visitor_team_name": "Raccoons 2",
      "visitor_goals": 3,
      "visitor_goals_string": "3",
      "home_team_name": "Army of Darkness",
      "home_goals": 4,
      "home_goals_string": "4",
      "game_won_in_shootout": false,
      "game_won_in_overtime": false,
      "type": "Regular"
    },
    {
      "game_id": 133245,
      "date": "2015-05-11",
      "datetime": "2015-05-11T23:15:00-08:00",
      "date_string": "Mon May 11",
      "time_string": "11:15 PM",
      "rink": "San Jose East",
      "hockey_league_name": "SIAHL@SJ",
      "division_name": "Senior DDDDD",
      "league": "SIAHL@SJ Senior DDDDD",
      "siahl_sj_league": "DDDDD",
      "visitor_team_name": "Raccoons 2",
      "visitor_goals": 1,
      "visitor_goals_string": "1",
      "home_team_name": "Night Hawks",
      "home_goals": 1,
      "home_goals_string": "1",
      "game_won_in_shootout": false,
      "game_won_in_overtime": false,
      "type": "Regular"
    },
    {
      "game_id": 133816,
      "date": "2015-05-17",
      "datetime": "2015-05-17T18:45:00-08:00",
      "date_string": "Sun May 17",
      "time_string": "6:45 PM",
      "rink": "San Jose East",
      "hockey_league_name": "SIAHL@SJ",
      "division_name": "Senior DDDDD",
      "league": "SIAHL@SJ Senior DDDDD",
      "siahl_sj_league": "DDDDD",
      "visitor_team_name": "Angry Beavers",
      "visitor_goals": 4,
      "visitor_goals_string": "4",
      "home_team_name": "Raccoons 2",
      "home_goals": 3,
      "home_goals_string": "3",
      "game_won_in_shootout": false,
      "game_won_in_overtime": false,
      "type": "Regular"
    },
    {
      "game_id": 133918,
      "date": "2015-05-24",
      "datetime": "2015-05-24T21:45:00-08:00",
      "date_string": "Sun May 24",
      "time_string": "9:45 PM",
      "rink": "San Jose North",
      "hockey_league_name": "SIAHL@SJ",
      "division_name": "Senior DDDDD",
      "league": "SIAHL@SJ Senior DDDDD",
      "siahl_sj_league": "DDDDD",
      "visitor_team_name": "Raccoons 2",
      "visitor_goals": 4,
      "visitor_goals_string": "4",
      "home_team_name": "Wolfpack",
      "home_goals": 0,
      "home_goals_string": "0",
      "game_won_in_shootout": false,
      "game_won_in_overtime": false,
      "type": "Regular"
    },
    {
      "game_id": 134161,
      "date": "2015-06-02",
      "datetime": "2015-06-02T23:15:00-08:00",
      "date_string": "Tue Jun 2",
      "time_string": "11:15 PM",
      "rink": "San Jose South",
      "hockey_league_name": "SIAHL@SJ",
      "division_name": "Senior DDDDD",
      "league": "SIAHL@SJ Senior DDDDD",
      "siahl_sj_league": "DDDDD",
      "visitor_team_name": "Buck Tooth Angry Dolphins",
      "visitor_goals": 1,
      "visitor_goals_string": "1",
      "home_team_name": "Raccoons 2",
      "home_goals": 5,
      "home_goals_string": "5",
      "game_won_in_shootout": false,
      "game_won_in_overtime": false,
      "type": "Regular"
    },
    {
      "game_id": 134357,
      "date": "2015-06-14",
      "datetime": "2015-06-14T15:30:00-08:00",
      "date_string": "Sun Jun 14",
      "time_string": "3:30 PM",
      "rink": "San Jose Center",
      "hockey_league_name": "SIAHL@SJ",
      "division_name": "Senior DDDDD",
      "league": "SIAHL@SJ Senior DDDDD",
      "siahl_sj_league": "DDDDD",
      "visitor_team_name": "Tyrannosaurs",
      "visitor_goals": 3,
      "visitor_goals_string": "3 S",
      "home_team_name": "Raccoons 2",
      "home_goals": 4,
      "home_goals_string": "4",
      "game_won_in_shootout": true,
      "game_won_in_overtime": false,
      "type": "Regular"
    },
    {
      "game_id": 134699,
      "date": "2015-06-15",
      "datetime": "2015-06-15T20:15:00-08:00",
      "date_string": "Mon Jun 15",
      "time_string": "8:15 PM",
      "rink": "San Jose North",
      "hockey_league_name": "SIAHL@SJ",
      "division_name": "Senior DDDDD",
      "league": "SIAHL@SJ Senior DDDDD",
      "siahl_sj_league": "DDDDD",
      "visitor_team_name": "Dunder Mifflin",
      "visitor_goals": 4,
      "visitor_goals_string": "4",
      "home_team_name": "Raccoons 2",
      "home_goals": 3,
      "home_goals_string": "3",
      "game_won_in_shootout": false,
      "game_won_in_overtime": false,
      "type": "Regular"
    },
    {
      "game_id": 134501,
      "date": "2015-06-23",
      "datetime": "2015-06-23T20:15:00-08:00",
      "date_string": "Tue Jun 23",
      "time_string": "8:15 PM",
      "rink": "San Jose North",
      "hockey_league_name": "SIAHL@SJ",
      "division_name": "Senior DDDDD",
      "league": "SIAHL@SJ Senior DDDDD",
      "siahl_sj_league": "DDDDD",
      "visitor_team_name": "Raccoons 2",
      "visitor_goals": 1,
      "visitor_goals_string": "1",
      "home_team_name": "Dunder Mifflin",
      "home_goals": 3,
      "home_goals_string": "3",
      "game_won_in_shootout": false,
      "game_won_in_overtime": false,
      "type": "Regular"
    },
    {
      "game_id": 134555,
      "date": "2015-06-27",
      "datetime": "2015-06-27T15:45:00-08:00",
      "date_string": "Sat Jun 27",
      "time_string": "3:45 PM",
      "rink": "San Jose South",
      "hockey_league_name": "SIAHL@SJ",
      "division_name": "Senior DDDDD",
      "league": "SIAHL@SJ Senior DDDDD",
      "siahl_sj_league": "DDDDD",
      "visitor_team_name": "Chieftains",
      "visitor_goals": 2,
      "visitor_goals_string": "2",
      "home_team_name": "Raccoons 2",
      "home_goals": 6,
      "home_goals_string": "6",
      "game_won_in_shootout": false,
      "game_won_in_overtime": false,
      "type": "Regular"
    },
    {
      "game_id": 134629,
      "date": "2015-06-29",
      "datetime": "2015-06-29T18:45:00-08:00",
      "date_string": "Mon Jun 29",
      "time_string": "6:45 PM",
      "rink": "San Jose South",
      "hockey_league_name": "SIAHL@SJ",
      "division_name": "Senior DDDDD",
      "league": "SIAHL@SJ Senior DDDDD",
      "siahl_sj_league": "DDDDD",
      "visitor_team_name": "Raccoons 2",
      "visitor_goals": 7,
      "visitor_goals_string": "7",
      "home_team_name": "Buck Tooth Angry Dolphins",
      "home_goals": 1,
      "home_goals_string": "1",
      "game_won_in_shootout": false,
      "game_won_in_overtime": false,
      "type": "Regular"
    },
    {
      "game_id": 134858,
      "date": "2015-07-11",
      "datetime": "2015-07-11T14:15:00-08:00",
      "date_string": "Sat Jul 11",
      "time_string": "2:15 PM",
      "rink": "San Jose East",
      "hockey_league_name": "SIAHL@SJ",
      "division_name": "Senior DDDDD",
      "league": "SIAHL@SJ Senior DDDDD",
      "siahl_sj_league": "DDDDD",
      "visitor_team_name": "Army of Darkness",
      "visitor_goals": 6,
      "visitor_goals_string": "6",
      "home_team_name": "Raccoons 2",
      "home_goals": 3,
      "home_goals_string": "3",
      "game_won_in_shootout": false,
      "game_won_in_overtime": false,
      "type": "Regular"
    },
    {
      "game_id": 135061,
      "date": "2015-07-19",
      "datetime": "2015-07-19T10:00:00-08:00",
      "date_string": "Sun Jul 19",
      "time_string": "10:00 AM",
      "rink": "San Jose East",
      "hockey_league_name": "SIAHL@SJ",
      "division_name": "Senior DDDDD",
      "league": "SIAHL@SJ Senior DDDDD",
      "siahl_sj_league": "DDDDD",
      "visitor_team_name": "Raccoons 2",
      "visitor_goals": 6,
      "visitor_goals_string": "6",
      "home_team_name": "Wolfpack",
      "home_goals": 4,
      "home_goals_string": "4",
      "game_won_in_shootout": false,
      "game_won_in_overtime": false,
      "type": "Regular"
    },
    {
      "game_id": 135111,
      "date": "2015-07-21",
      "datetime": "2015-07-21T19:45:00-08:00",
      "date_string": "Tue Jul 21",
      "time_string": "7:45 PM",
      "rink": "San Jose North",
      "hockey_league_name": "SIAHL@SJ",
      "division_name": "Senior DDDDD",
      "league": "SIAHL@SJ Senior DDDDD",
      "siahl_sj_league": "DDDDD",
      "visitor_team_name": "Raccoons 2",
      "visitor_goals": 3,
      "visitor_goals_string": "3",
      "home_team_name": "Chieftains",
      "home_goals": 1,
      "home_goals_string": "1",
      "game_won_in_shootout": false,
      "game_won_in_overtime": false,
      "type": "Regular"
    },
    {
      "game_id": 135736,
      "date": "2015-07-25",
      "datetime": "2015-07-25T18:15:00-08:00",
      "date_string": "Sat Jul 25",
      "time_string": "6:15 PM",
      "rink": "San Jose North",
      "hockey_league_name": "SIAHL@SJ",
      "division_name": "Senior DDDDD",
      "league": "SIAHL@SJ Senior DDDDD",
      "siahl_sj_league": "DDDDD",
      "visitor_team_name": "Tyrannosaurs",
      "visitor_goals": 1,
      "visitor_goals_string": "1",
      "home_team_name": "Raccoons 2",
      "home_goals": 2,
      "home_goals_string": "2",
      "game_won_in_shootout": false,
      "game_won_in_overtime": false,
      "type": "Regular"
    },
    {
      "game_id": 135909,
      "date": "2015-08-02",
      "datetime": "2015-08-02T15:45:00-08:00",
      "date_string": "Sun Aug 2",
      "time_string": "3:45 PM",
      "rink": "San Jose Center",
      "hockey_league_name": "SIAHL@SJ",
      "division_name": "Senior DDDDD",
      "league": "SIAHL@SJ Senior DDDDD",
      "siahl_sj_league": "DDDDD",
      "visitor_team_name": "Angry Beavers",
      "visitor_goals": 0,
      "visitor_goals_string": "0",
      "home_team_name": "Raccoons 2",
      "home_goals": 5,
      "home_goals_string": "5",
      "game_won_in_shootout": false,
      "game_won_in_overtime": false,
      "type": "Regular"
    },
    {
      "game_id": "136087",
      "date": "",
      "datetime": "",
      "date_string": "Mon Aug 10",
      "time_string": "8:00 PM",
      "rink": "San Jose South",
      "hockey_league_name": "SIAHL@SJ",
      "division_name": "Senior DDDDD",
      "league": "SIAHL@SJ Senior DDDDD",
      "siahl_sj_league": "DDDDD",
      "visitor_team_name": "Night Hawks",
      "visitor_goals": 0,
      "visitor_goals_string": "",
      "home_team_name": "Raccoons 2",
      "home_goals": 0,
      "home_goals_string": "",
      "game_won_in_shootout": false,
      "game_won_in_overtime": false,
      "type": "Regular"
    }
  ],
  "skaters": [
    {
      "name": "John Duffy",
      "number": "27",
      "rostered_player": true,
      "games_played": 13,
      "goals": 8,
      "assists": 6,
      "power_play_goals": 0,
      "power_play_assists": 4,
      "short_handed_goals": 1,
      "short_handed_assists": 0,
      "game_winning_goal": 2,
      "game_winning_assists": 1,
      "penalty_shot_goals": 0,
      "empty_net_goals": 2,
      "shots_on_goal": 0,
      "is_goalie": false
    },
    {
      "name": "Jeffrey Lam",
      "number": "79",
      "rostered_player": true,
      "games_played": 11,
      "goals": 8,
      "assists": 4,
      "power_play_goals": 0,
      "power_play_assists": 0,
      "short_handed_goals": 0,
      "short_handed_assists": 0,
      "game_winning_goal": 1,
      "game_winning_assists": 0,
      "penalty_shot_goals": 0,
      "empty_net_goals": 2,
      "shots_on_goal": 0,
      "is_goalie": false
    },
    {
      "name": "Timothy Lynn",
      "number": "21",
      "rostered_player": true,
      "games_played": 10,
      "goals": 5,
      "assists": 5,
      "power_play_goals": 1,
      "power_play_assists": 0,
      "short_handed_goals": 0,
      "short_handed_assists": 0,
      "game_winning_goal": 0,
      "game_winning_assists": 0,
      "penalty_shot_goals": 0,
      "empty_net_goals": 0,
      "shots_on_goal": 0,
      "is_goalie": false
    },
    {
      "name": "Matthew Miller",
      "number": "14",
      "rostered_player": true,
      "games_played": 14,
      "goals": 5,
      "assists": 5,
      "power_play_goals": 1,
      "power_play_assists": 0,
      "short_handed_goals": 0,
      "short_handed_assists": 0,
      "game_winning_goal": 0,
      "game_winning_assists": 0,
      "penalty_shot_goals": 0,
      "empty_net_goals": 0,
      "shots_on_goal": 0,
      "is_goalie": false
    },
    {
      "name": "Ryan Newberry",
      "number": "47",
      "rostered_player": true,
      "games_played": 10,
      "goals": 4,
      "assists": 6,
      "power_play_goals": 1,
      "power_play_assists": 0,
      "short_handed_goals": 0,
      "short_handed_assists": 0,
      "game_winning_goal": 0,
      "game_winning_assists": 1,
      "penalty_shot_goals": 0,
      "empty_net_goals": 0,
      "shots_on_goal": 0,
      "is_goalie": false
    },
    {
      "name": "David Marshall",
      "number": "19",
      "rostered_player": true,
      "games_played": 10,
      "goals": 6,
      "assists": 3,
      "power_play_goals": 0,
      "power_play_assists": 0,
      "short_handed_goals": 0,
      "short_handed_assists": 1,
      "game_winning_goal": 1,
      "game_winning_assists": 1,
      "penalty_shot_goals": 0,
      "empty_net_goals": 3,
      "shots_on_goal": 0,
      "is_goalie": false
    },
    {
      "name": "Jared Rifa",
      "number": "37",
      "rostered_player": true,
      "games_played": 10,
      "goals": 5,
      "assists": 2,
      "power_play_goals": 0,
      "power_play_assists": 0,
      "short_handed_goals": 1,
      "short_handed_assists": 0,
      "game_winning_goal": 1,
      "game_winning_assists": 0,
      "penalty_shot_goals": 0,
      "empty_net_goals": 1,
      "shots_on_goal": 0,
      "is_goalie": false
    },
    {
      "name": "Jeff Freeland",
      "number": "47",
      "rostered_player": true,
      "games_played": 7,
      "goals": 0,
      "assists": 6,
      "power_play_goals": 0,
      "power_play_assists": 0,
      "short_handed_goals": 0,
      "short_handed_assists": 0,
      "game_winning_goal": 0,
      "game_winning_assists": 1,
      "penalty_shot_goals": 0,
      "empty_net_goals": 0,
      "shots_on_goal": 0,
      "is_goalie": false
    },
    {
      "name": "Pedro Velasco",
      "number": "42",
      "rostered_player": true,
      "games_played": 12,
      "goals": 2,
      "assists": 4,
      "power_play_goals": 0,
      "power_play_assists": 0,
      "short_handed_goals": 1,
      "short_handed_assists": 0,
      "game_winning_goal": 0,
      "game_winning_assists": 1,
      "penalty_shot_goals": 0,
      "empty_net_goals": 0,
      "shots_on_goal": 0,
      "is_goalie": false
    },
    {
      "name": "David-Kim Nguyen",
      "number": "83",
      "rostered_player": true,
      "games_played": 10,
      "goals": 0,
      "assists": 5,
      "power_play_goals": 0,
      "power_play_assists": 0,
      "short_handed_goals": 0,
      "short_handed_assists": 0,
      "game_winning_goal": 0,
      "game_winning_assists": 1,
      "penalty_shot_goals": 0,
      "empty_net_goals": 0,
      "shots_on_goal": 0,
      "is_goalie": false
    },
    {
      "name": "Michael Sprague",
      "number": "25",
      "rostered_player": true,
      "games_played": 12,
      "goals": 4,
      "assists": 1,
      "power_play_goals": 0,
      "power_play_assists": 0,
      "short_handed_goals": 0,
      "short_handed_assists": 0,
      "game_winning_goal": 1,
      "game_winning_assists": 0,
      "penalty_shot_goals": 0,
      "empty_net_goals": 1,
      "shots_on_goal": 0,
      "is_goalie": false
    },
    {
      "name": "Ryan Horn",
      "number": "21",
      "rostered_player": true,
      "games_played": 11,
      "goals": 2,
      "assists": 2,
      "power_play_goals": 0,
      "power_play_assists": 1,
      "short_handed_goals": 0,
      "short_handed_assists": 0,
      "game_winning_goal": 0,
      "game_winning_assists": 0,
      "penalty_shot_goals": 0,
      "empty_net_goals": 0,
      "shots_on_goal": 0,
      "is_goalie": false
    },
    {
      "name": "William Kessler",
      "number": "20",
      "rostered_player": true,
      "games_played": 9,
      "goals": 2,
      "assists": 2,
      "power_play_goals": 1,
      "power_play_assists": 0,
      "short_handed_goals": 0,
      "short_handed_assists": 0,
      "game_winning_goal": 0,
      "game_winning_assists": 2,
      "penalty_shot_goals": 0,
      "empty_net_goals": 0,
      "shots_on_goal": 0,
      "is_goalie": false
    },
    {
      "name": "Christian Scott",
      "number": "88",
      "rostered_player": true,
      "games_played": 12,
      "goals": 0,
      "assists": 4,
      "power_play_goals": 0,
      "power_play_assists": 0,
      "short_handed_goals": 0,
      "short_handed_assists": 0,
      "game_winning_goal": 0,
      "game_winning_assists": 1,
      "penalty_shot_goals": 0,
      "empty_net_goals": 0,
      "shots_on_goal": 0,
      "is_goalie": false
    },
    {
      "name": "PAUL ROUSSEVE",
      "number": "9",
      "rostered_player": true,
      "games_played": 4,
      "goals": 1,
      "assists": 2,
      "power_play_goals": 0,
      "power_play_assists": 1,
      "short_handed_goals": 0,
      "short_handed_assists": 0,
      "game_winning_goal": 1,
      "game_winning_assists": 1,
      "penalty_shot_goals": 0,
      "empty_net_goals": 0,
      "shots_on_goal": 0,
      "is_goalie": false
    },
    {
      "name": "John Digiovanni Ii",
      "number": "61",
      "rostered_player": true,
      "games_played": 3,
      "goals": 2,
      "assists": 0,
      "power_play_goals": 0,
      "power_play_assists": 0,
      "short_handed_goals": 1,
      "short_handed_assists": 0,
      "game_winning_goal": 1,
      "game_winning_assists": 0,
      "penalty_shot_goals": 0,
      "empty_net_goals": 1,
      "shots_on_goal": 0,
      "is_goalie": false
    },
    {
      "name": "LEONARDO PASKIN",
      "number": "71",
      "rostered_player": true,
      "games_played": 5,
      "goals": 1,
      "assists": 1,
      "power_play_goals": 1,
      "power_play_assists": 0,
      "short_handed_goals": 0,
      "short_handed_assists": 0,
      "game_winning_goal": 0,
      "game_winning_assists": 0,
      "penalty_shot_goals": 0,
      "empty_net_goals": 0,
      "shots_on_goal": 0,
      "is_goalie": false
    },
    {
      "name": "RYAN SEIBERT",
      "number": "85",
      "rostered_player": true,
      "games_played": 7,
      "goals": 0,
      "assists": 2,
      "power_play_goals": 0,
      "power_play_assists": 0,
      "short_handed_goals": 0,
      "short_handed_assists": 0,
      "game_winning_goal": 0,
      "game_winning_assists": 0,
      "penalty_shot_goals": 0,
      "empty_net_goals": 0,
      "shots_on_goal": 0,
      "is_goalie": false
    },
    {
      "name": "Neil Radia",
      "number": "18",
      "rostered_player": true,
      "games_played": 5,
      "goals": 0,
      "assists": 1,
      "power_play_goals": 0,
      "power_play_assists": 0,
      "short_handed_goals": 0,
      "short_handed_assists": 0,
      "game_winning_goal": 0,
      "game_winning_assists": 1,
      "penalty_shot_goals": 0,
      "empty_net_goals": 0,
      "shots_on_goal": 0,
      "is_goalie": false
    },
    {
      "name": "Yuri Macauley",
      "number": "",
      "rostered_player": false,
      "games_played": 1,
      "goals": 0,
      "assists": 0,
      "power_play_goals": 0,
      "power_play_assists": 0,
      "short_handed_goals": 0,
      "short_handed_assists": 0,
      "game_winning_goal": 0,
      "game_winning_assists": 0,
      "penalty_shot_goals": 0,
      "empty_net_goals": 0,
      "shots_on_goal": 0,
      "is_goalie": false
    },
    {
      "name": "Jonathan Simmons",
      "number": "",
      "rostered_player": false,
      "games_played": 1,
      "goals": 0,
      "assists": 0,
      "power_play_goals": 0,
      "power_play_assists": 0,
      "short_handed_goals": 0,
      "short_handed_assists": 0,
      "game_winning_goal": 0,
      "game_winning_assists": 0,
      "penalty_shot_goals": 0,
      "empty_net_goals": 0,
      "shots_on_goal": 0,
      "is_goalie": false
    },
    {
      "name": "NICKLAUS TORRECILLAS",
      "number": "69",
      "rostered_player": true,
      "games_played": 5,
      "goals": 0,
      "assists": 0,
      "power_play_goals": 0,
      "power_play_assists": 0,
      "short_handed_goals": 0,
      "short_handed_assists": 0,
      "game_winning_goal": 0,
      "game_winning_assists": 0,
      "penalty_shot_goals": 0,
      "empty_net_goals": 0,
      "shots_on_goal": 0,
      "is_goalie": false
    }
  ],
  "goalies": [
    {
      "name": "PHILLIP E LINARTE",
      "number": "31",
      "rostered_player": true,
      "games_played": 10,
      "shots_against": 239,
      "goals_against": 19,
      "goals_against_average": 1.9,
      "save_percentage": 0.921,
      "goals": 0,
      "assists": 0,
      "points": 0,
      "is_goalie": true
    },
    {
      "name": "PAUL N ROUSSEVE",
      "number": "9",
      "rostered_player": true,
      "games_played": 3,
      "shots_against": 77,
      "goals_against": 11,
      "goals_against_average": 3.67,
      "save_percentage": 0.857,
      "goals": 0,
      "assists": 0,
      "points": 0,
      "is_goalie": true
    }
  ]
}
